{
    "plane": "mgmt-plane",
    "resources": [
        {
            "id": "/{resourceuri}/providers/microsoft.insights/diagnosticsettings",
            "version": "2021-05-01-preview",
            "swagger": "mgmt-plane/monitor/ResourceProviders/Microsoft.Insights/Paths/L3tyZXNvdXJjZVVyaX0vcHJvdmlkZXJzL01pY3Jvc29mdC5JbnNpZ2h0cy9kaWFnbm9zdGljU2V0dGluZ3M=/V/MjAyMS0wNS0wMS1wcmV2aWV3"
        }
    ],
    "commandGroups": [
        {
            "name": "monitor diagnostic-settings",
            "commands": [
                {
                    "name": "list",
                    "version": "2021-05-01-preview",
                    "resources": [
                        {
                            "id": "/{resourceuri}/providers/microsoft.insights/diagnosticsettings",
                            "version": "2021-05-01-preview",
                            "swagger": "mgmt-plane/monitor/ResourceProviders/Microsoft.Insights/Paths/L3tyZXNvdXJjZVVyaX0vcHJvdmlkZXJzL01pY3Jvc29mdC5JbnNpZ2h0cy9kaWFnbm9zdGljU2V0dGluZ3M=/V/MjAyMS0wNS0wMS1wcmV2aWV3"
                        }
                    ],
                    "argGroups": [
                        {
                            "name": "",
                            "args": [
                                {
                                    "type": "string",
                                    "var": "$Path.resourceUri",
                                    "options": [
                                        "resource"
                                    ],
                                    "required": true,
                                    "group": "",
                                    "help": {
                                        "short": "Name or ID of the target resource."
                                    }
                                }
                            ]
                        }
                    ],
                    "operations": [
                        {
                            "operationId": "DiagnosticSettings_List",
                            "http": {
                                "path": "/{resourceUri}/providers/Microsoft.Insights/diagnosticSettings",
                                "request": {
                                    "method": "get",
                                    "path": {
                                        "params": [
                                            {
                                                "type": "string",
                                                "name": "resourceUri",
                                                "arg": "$Path.resourceUri",
                                                "required": true,
                                                "skipUrlEncoding": true
                                            }
                                        ]
                                    },
                                    "query": {
                                        "consts": [
                                            {
                                                "readOnly": true,
                                                "const": true,
                                                "default": {
                                                    "value": "2021-05-01-preview"
                                                },
                                                "type": "string",
                                                "name": "api-version",
                                                "required": true,
                                                "format": {
                                                    "minLength": 1
                                                }
                                            }
                                        ]
                                    }
                                },
                                "responses": [
                                    {
                                        "statusCode": [
                                            200
                                        ],
                                        "body": {
                                            "json": {
                                                "var": "$Instance",
                                                "schema": {
                                                    "type": "object",
                                                    "props": [
                                                        {
                                                            "type": "array<object>",
                                                            "name": "value",
                                                            "item": {
                                                                "type": "object",
                                                                "props": [
                                                                    {
                                                                        "readOnly": true,
                                                                        "type": "ResourceId",
                                                                        "name": "id",
                                                                        "format": {
                                                                            "template": "/{resourceUri}/providers/Microsoft.Insights/diagnosticSettings/{}"
                                                                        }
                                                                    },
                                                                    {
                                                                        "readOnly": true,
                                                                        "type": "string",
                                                                        "name": "name"
                                                                    },
                                                                    {
                                                                        "type": "object",
                                                                        "name": "properties",
                                                                        "props": [
                                                                            {
                                                                                "type": "string",
                                                                                "name": "eventHubAuthorizationRuleId"
                                                                            },
                                                                            {
                                                                                "type": "string",
                                                                                "name": "eventHubName"
                                                                            },
                                                                            {
                                                                                "type": "string",
                                                                                "name": "logAnalyticsDestinationType"
                                                                            },
                                                                            {
                                                                                "type": "array<object>",
                                                                                "name": "logs",
                                                                                "item": {
                                                                                    "type": "object",
                                                                                    "props": [
                                                                                        {
                                                                                            "type": "string",
                                                                                            "name": "category"
                                                                                        },
                                                                                        {
                                                                                            "type": "string",
                                                                                            "name": "categoryGroup"
                                                                                        },
                                                                                        {
                                                                                            "type": "boolean",
                                                                                            "name": "enabled",
                                                                                            "required": true
                                                                                        },
                                                                                        {
                                                                                            "type": "@RetentionPolicy_read",
                                                                                            "name": "retentionPolicy"
                                                                                        }
                                                                                    ]
                                                                                }
                                                                            },
                                                                            {
                                                                                "type": "string",
                                                                                "name": "marketplacePartnerId"
                                                                            },
                                                                            {
                                                                                "type": "array<object>",
                                                                                "name": "metrics",
                                                                                "item": {
                                                                                    "type": "object",
                                                                                    "props": [
                                                                                        {
                                                                                            "type": "string",
                                                                                            "name": "category"
                                                                                        },
                                                                                        {
                                                                                            "type": "boolean",
                                                                                            "name": "enabled",
                                                                                            "required": true
                                                                                        },
                                                                                        {
                                                                                            "type": "object",
                                                                                            "name": "retentionPolicy",
                                                                                            "props": [
                                                                                                {
                                                                                                    "type": "integer32",
                                                                                                    "name": "days",
                                                                                                    "required": true,
                                                                                                    "format": {
                                                                                                        "minimum": 0
                                                                                                    }
                                                                                                },
                                                                                                {
                                                                                                    "type": "boolean",
                                                                                                    "name": "enabled",
                                                                                                    "required": true
                                                                                                }
                                                                                            ],
                                                                                            "cls": "RetentionPolicy_read"
                                                                                        },
                                                                                        {
                                                                                            "type": "duration",
                                                                                            "name": "timeGrain"
                                                                                        }
                                                                                    ]
                                                                                }
                                                                            },
                                                                            {
                                                                                "type": "string",
                                                                                "name": "serviceBusRuleId"
                                                                            },
                                                                            {
                                                                                "type": "string",
                                                                                "name": "storageAccountId"
                                                                            },
                                                                            {
                                                                                "type": "string",
                                                                                "name": "workspaceId"
                                                                            }
                                                                        ],
                                                                        "clientFlatten": true
                                                                    },
                                                                    {
                                                                        "readOnly": true,
                                                                        "type": "object",
                                                                        "name": "systemData",
                                                                        "props": [
                                                                            {
                                                                                "type": "dateTime",
                                                                                "name": "createdAt"
                                                                            },
                                                                            {
                                                                                "type": "string",
                                                                                "name": "createdBy"
                                                                            },
                                                                            {
                                                                                "type": "string",
                                                                                "name": "createdByType",
                                                                                "enum": {
                                                                                    "items": [
                                                                                        {
                                                                                            "value": "Application"
                                                                                        },
                                                                                        {
                                                                                            "value": "Key"
                                                                                        },
                                                                                        {
                                                                                            "value": "ManagedIdentity"
                                                                                        },
                                                                                        {
                                                                                            "value": "User"
                                                                                        }
                                                                                    ]
                                                                                }
                                                                            },
                                                                            {
                                                                                "type": "dateTime",
                                                                                "name": "lastModifiedAt"
                                                                            },
                                                                            {
                                                                                "type": "string",
                                                                                "name": "lastModifiedBy"
                                                                            },
                                                                            {
                                                                                "type": "string",
                                                                                "name": "lastModifiedByType",
                                                                                "enum": {
                                                                                    "items": [
                                                                                        {
                                                                                            "value": "Application"
                                                                                        },
                                                                                        {
                                                                                            "value": "Key"
                                                                                        },
                                                                                        {
                                                                                            "value": "ManagedIdentity"
                                                                                        },
                                                                                        {
                                                                                            "value": "User"
                                                                                        }
                                                                                    ]
                                                                                }
                                                                            }
                                                                        ]
                                                                    },
                                                                    {
                                                                        "readOnly": true,
                                                                        "type": "string",
                                                                        "name": "type"
                                                                    }
                                                                ]
                                                            }
                                                        }
                                                    ]
                                                }
                                            }
                                        }
                                    },
                                    {
                                        "isError": true,
                                        "body": {
                                            "json": {
                                                "schema": {
                                                    "type": "@ODataV4Format"
                                                }
                                            }
                                        }
                                    }
                                ]
                            }
                        }
                    ],
                    "outputs": [
                        {
                            "type": "array",
                            "ref": "$Instance.value",
                            "clientFlatten": true
                        }
                    ],
                    "confirmation": ""
                }
            ]
        }
    ]
}