{"plane": "mgmt-plane", "resources": [{"id": "/{scope}/providers/microsoft.quota/usages/{}", "version": "2023-02-01", "swagger": "mgmt-plane/quota/ResourceProviders/Microsoft.Quota/Paths/L3tzY29wZX0vcHJvdmlkZXJzL01pY3Jvc29mdC5RdW90YS91c2FnZXMve3Jlc291cmNlTmFtZX0=/V/MjAyMy0wMi0wMQ=="}], "commandGroups": [{"name": "quota usage", "commands": [{"name": "show", "version": "2023-02-01", "resources": [{"id": "/{scope}/providers/microsoft.quota/usages/{}", "version": "2023-02-01", "swagger": "mgmt-plane/quota/ResourceProviders/Microsoft.Quota/Paths/L3tzY29wZX0vcHJvdmlkZXJzL01pY3Jvc29mdC5RdW90YS91c2FnZXMve3Jlc291cmNlTmFtZX0=/V/MjAyMy0wMi0wMQ=="}], "argGroups": [{"name": "", "args": [{"type": "string", "var": "$Path.resourceName", "options": ["resource-name"], "required": true, "group": "", "help": {"short": "Resource name for a given resource provider."}}, {"type": "string", "var": "$Path.scope", "options": ["scope"], "required": true, "group": "", "help": {"short": "The target azure resource URI."}}]}], "operations": [{"operationId": "Usages_Get", "http": {"path": "/{scope}/providers/Microsoft.Quota/usages/{resourceName}", "request": {"method": "get", "path": {"params": [{"type": "string", "name": "resourceName", "arg": "$Path.resourceName", "required": true}, {"type": "string", "name": "scope", "arg": "$Path.scope", "required": true, "skipUrlEncoding": true}]}, "query": {"consts": [{"readOnly": true, "const": true, "default": {"value": "2023-02-01"}, "type": "string", "name": "api-version", "required": true, "format": {"minLength": 1}}]}}, "responses": [{"statusCode": [200], "header": {"items": [{"name": "ETag"}]}, "body": {"json": {"var": "$Instance", "schema": {"type": "object", "props": [{"readOnly": true, "type": "ResourceId", "name": "id", "format": {"template": "/{scope}/providers/Microsoft.Quota/usages/{}"}}, {"readOnly": true, "type": "string", "name": "name"}, {"type": "object", "name": "properties", "props": [{"readOnly": true, "type": "boolean", "name": "isQuotaApplicable"}, {"type": "object", "name": "name", "props": [{"readOnly": true, "type": "string", "name": "localizedValue"}, {"type": "string", "name": "value"}]}, {"type": "object", "name": "properties", "additionalProps": {"anyType": true}}, {"readOnly": true, "type": "string", "name": "quotaPeriod"}, {"type": "string", "name": "resourceType"}, {"readOnly": true, "type": "string", "name": "unit"}, {"type": "object", "name": "usages", "props": [{"type": "string", "name": "usagesType", "enum": {"items": [{"value": "Combined"}, {"value": "Individual"}]}}, {"type": "integer32", "name": "value", "required": true}]}]}, {"readOnly": true, "type": "string", "name": "type"}]}}}}, {"isError": true, "body": {"json": {"schema": {"type": "@ODataV4Format"}}}}]}}], "outputs": [{"type": "object", "ref": "$Instance", "clientFlatten": true}], "confirmation": ""}]}]}