{"plane": "mgmt-plane", "resources": [{"id": "/subscriptions/{}/providers/microsoft.network/locations/{}/applicationgatewaywafdynamicmanifests", "version": "2022-05-01", "swagger": "mgmt-plane/network/ResourceProviders/Microsoft.Network/Paths/L3N1YnNjcmlwdGlvbnMve3N1YnNjcmlwdGlvbklkfS9wcm92aWRlcnMvTWljcm9zb2Z0Lk5ldHdvcmsvbG9jYXRpb25zL3tsb2NhdGlvbn0vYXBwbGljYXRpb25HYXRld2F5V2FmRHluYW1pY01hbmlmZXN0cw==/V/MjAyMi0wNS0wMQ=="}], "commandGroups": [{"name": "network application-gateway waf-config", "commands": [{"name": "list-dynamic-rule-sets", "version": "2022-05-01", "resources": [{"id": "/subscriptions/{}/providers/microsoft.network/locations/{}/applicationgatewaywafdynamicmanifests", "version": "2022-05-01", "swagger": "mgmt-plane/network/ResourceProviders/Microsoft.Network/Paths/L3N1YnNjcmlwdGlvbnMve3N1YnNjcmlwdGlvbklkfS9wcm92aWRlcnMvTWljcm9zb2Z0Lk5ldHdvcmsvbG9jYXRpb25zL3tsb2NhdGlvbn0vYXBwbGljYXRpb25HYXRld2F5V2FmRHluYW1pY01hbmlmZXN0cw==/V/MjAyMi0wNS0wMQ=="}], "argGroups": [{"name": "", "args": [{"type": "ResourceLocation", "var": "$Path.location", "options": ["l", "location"], "required": true, "idPart": "name"}, {"type": "SubscriptionId", "var": "$Path.subscriptionId", "options": ["subscription"], "required": true, "idPart": "subscription"}]}], "operations": [{"operationId": "ApplicationGatewayWafDynamicManifests_Get", "http": {"path": "/subscriptions/{subscriptionId}/providers/Microsoft.Network/locations/{location}/applicationGatewayWafDynamicManifests", "request": {"method": "get", "path": {"params": [{"type": "string", "name": "location", "arg": "$Path.location", "required": true}, {"type": "string", "name": "subscriptionId", "arg": "$Path.subscriptionId", "required": true}]}, "query": {"consts": [{"readOnly": true, "const": true, "default": {"value": "2022-05-01"}, "type": "string", "name": "api-version", "required": true}]}}, "responses": [{"statusCode": [200], "body": {"json": {"var": "$Instance", "schema": {"type": "object", "props": [{"type": "string", "name": "nextLink"}, {"type": "array<object>", "name": "value", "item": {"type": "object", "props": [{"type": "string", "name": "id"}, {"readOnly": true, "type": "string", "name": "name"}, {"type": "object", "name": "properties", "props": [{"type": "array<object>", "name": "availableRuleSets", "item": {"type": "object", "props": [{"type": "array<object>", "name": "ruleGroups", "required": true, "item": {"type": "object", "props": [{"type": "string", "name": "description"}, {"type": "string", "name": "ruleGroupName", "required": true}, {"type": "array<object>", "name": "rules", "required": true, "item": {"type": "object", "props": [{"type": "string", "name": "action", "enum": {"items": [{"value": "Allow"}, {"value": "AnomalyScoring"}, {"value": "Block"}, {"value": "Log"}, {"value": "None"}]}}, {"type": "string", "name": "description"}, {"type": "integer32", "name": "ruleId", "required": true}, {"type": "string", "name": "ruleIdString"}, {"type": "string", "name": "state", "enum": {"items": [{"value": "Disabled"}, {"value": "Enabled"}]}}]}}]}}, {"type": "string", "name": "ruleSetType", "required": true}, {"type": "string", "name": "ruleSetVersion", "required": true}, {"type": "string", "name": "status", "enum": {"items": [{"value": "Deprecated"}, {"value": "GA"}, {"value": "Preview"}, {"value": "Supported"}]}}, {"type": "array<string>", "name": "tiers", "item": {"type": "string", "enum": {"items": [{"value": "Standard"}, {"value": "Standard_v2"}, {"value": "WAF"}, {"value": "WAF_v2"}]}}}]}}, {"type": "object", "name": "defaultRuleSet", "props": [{"type": "string", "name": "ruleSetType"}, {"type": "string", "name": "ruleSetVersion"}], "clientFlatten": true}], "clientFlatten": true}, {"readOnly": true, "type": "string", "name": "type"}]}}]}}}}, {"isError": true, "body": {"json": {"schema": {"type": "@ODataV4Format"}}}}]}}], "outputs": [{"type": "array", "ref": "$Instance.value", "clientFlatten": true, "nextLink": "$Instance.nextLink"}], "confirmation": ""}]}]}